{
  "users": [
    {
      "id": "9b8c7d6e-5f4a-4b3c-8a7d-6e5f4a3b2c1d",
      "name": "Laura",
      "surname": "Pérez",
      "mail": "laura@example.com"
    },
    {
      "id": "2a3b4c5d-6e7f-4a8b-9c0d-1e2f3a4b5c6d",
      "name": "Marcos",
      "surname": "López",
      "mail": "marcos@example.com"
    },
    {
      "id": "c1d2e3f4-5a6b-4c7d-8e9f-0a1b2c3d4e5f",
      "name": "Iria",
      "surname": "Varela",
      "mail": "iria@example.com"
    },
    {
      "id": "0f1e2d3c-4b5a-4756-8d9c-0b1a2c3d4e5f",
      "name": "Noa",
      "surname": "Santos",
      "mail": "noa@example.com"
    }
  ]
}